MANIFEST.in
README.rst
nuclai
setup.py
nuclai/__init__.py
nuclai/__main__.py
nuclai/bootstrap.py
nuclai.egg-info/PKG-INFO
nuclai.egg-info/SOURCES.txt
nuclai.egg-info/dependency_links.txt
nuclai.egg-info/top_level.txt
nuclai/data/questrial.ttf
scripts/nuclai
scripts/nuclai.bat