Metadata-Version: 1.1
Name: nuclai
Version: 0.6
Summary: Cross-platform Installer & Runner for nucl.ai tutorials and excercises.
Home-page: https://github.com/aigamedev/nuclai-installer
Author: Alex J. Champandard
Author-email: UNKNOWN
License: GNU GPLv3
Platform: UNKNOWN
Classifier: Development Status :: 3 - Alpha
Classifier: Programming Language :: Python :: 3.4
Classifier: License :: Free For Home Use
Classifier: Topic :: Scientific/Engineering :: Artificial Intelligence
